{ "height":1,
 "infinite":true,
 "layers":[
        {
         "draworder":"topdown",
         "id":3,
         "name":"Basic Fighter Exhausts",
         "objects":[
                {
                 "gid":2,
                 "height":22.1538,
                 "id":6,
                 "name":"Rear Exhaust",
                 "rotation":180,
                 "type":"",
                 "visible":true,
                 "width":72,
                 "x":-83,
                 "y":4
                }, 
                {
                 "gid":2,
                 "height":22.1538,
                 "id":5,
                 "name":"Rear Exhaust",
                 "rotation":180,
                 "type":"",
                 "visible":true,
                 "width":72,
                 "x":-83,
                 "y":-26
                }, 
                {
                 "gid":2,
                 "height":6,
                 "id":8,
                 "name":"Rear Right Exhaust",
                 "rotation":90,
                 "type":"",
                 "visible":true,
                 "width":19.5,
                 "x":-87,
                 "y":77
                }, 
                {
                 "gid":2,
                 "height":6,
                 "id":7,
                 "name":"Rear Left Exhaust",
                 "rotation":-90,
                 "type":"",
                 "visible":true,
                 "width":19.5,
                 "x":-81,
                 "y":-76
                }, 
                {
                 "gid":2,
                 "height":6,
                 "id":10,
                 "name":"Front Right Exhaust",
                 "rotation":90,
                 "type":"",
                 "visible":true,
                 "width":19.5,
                 "x":44,
                 "y":14
                }, 
                {
                 "gid":2,
                 "height":6,
                 "id":9,
                 "name":"Front Left Exhaust",
                 "rotation":-90,
                 "type":"",
                 "visible":true,
                 "width":19.5,
                 "x":50,
                 "y":-12
                }, 
                {
                 "gid":2,
                 "height":11,
                 "id":4,
                 "name":"Front Exhaust",
                 "rotation":0,
                 "type":"",
                 "visible":true,
                 "width":35.75,
                 "x":-53,
                 "y":58
                }, 
                {
                 "gid":2,
                 "height":11,
                 "id":3,
                 "name":"Front Exhaust",
                 "rotation":0,
                 "type":"",
                 "visible":true,
                 "width":35.75,
                 "x":-53,
                 "y":-47
                }],
         "opacity":1,
         "type":"objectgroup",
         "visible":true,
         "x":0,
         "y":0
        }, 
        {
         "draworder":"topdown",
         "id":2,
         "name":"Basic Fighter Hull",
         "objects":[
                {
                 "gid":1,
                 "height":200,
                 "id":2,
                 "name":"Ship Hull",
                 "rotation":0,
                 "type":"",
                 "visible":true,
                 "width":200,
                 "x":-100,
                 "y":100
                }],
         "opacity":1,
         "type":"objectgroup",
         "visible":true,
         "x":0,
         "y":0
        }],
 "nextlayerid":4,
 "nextobjectid":11,
 "orientation":"orthogonal",
 "renderorder":"right-down",
 "tiledversion":"1.2.1",
 "tileheight":200,
 "tilesets":[
        {
         "columns":1,
         "firstgid":1,
         "image":"..\/..\/..\/Client\/Textures\/Ships\/basic_ships.png",
         "imageheight":200,
         "imagewidth":200,
         "margin":0,
         "name":"Ships",
         "spacing":0,
         "tilecount":1,
         "tileheight":200,
         "tiles":[
                {
                 "id":0,
                 "objectgroup":
                    {
                     "draworder":"index",
                     "name":"",
                     "objects":[
                            {
                             "height":0,
                             "id":1,
                             "name":"",
                             "polygon":[
                                    {
                                     "x":0,
                                     "y":0
                                    }, 
                                    {
                                     "x":-13,
                                     "y":-9
                                    }, 
                                    {
                                     "x":-13,
                                     "y":-19
                                    }, 
                                    {
                                     "x":10,
                                     "y":-29
                                    }, 
                                    {
                                     "x":67,
                                     "y":-27
                                    }, 
                                    {
                                     "x":86,
                                     "y":-12
                                    }, 
                                    {
                                     "x":86,
                                     "y":1
                                    }],
                             "rotation":0,
                             "type":"",
                             "visible":true,
                             "width":0,
                             "x":29,
                             "y":99
                            }, 
                            {
                             "height":0,
                             "id":2,
                             "name":"",
                             "polygon":[
                                    {
                                     "x":0,
                                     "y":0
                                    }, 
                                    {
                                     "x":-13,
                                     "y":11
                                    }, 
                                    {
                                     "x":-13,
                                     "y":21
                                    }, 
                                    {
                                     "x":8,
                                     "y":31
                                    }, 
                                    {
                                     "x":67,
                                     "y":30
                                    }, 
                                    {
                                     "x":86,
                                     "y":16
                                    }, 
                                    {
                                     "x":86,
                                     "y":1
                                    }],
                             "rotation":0,
                             "type":"",
                             "visible":true,
                             "width":0,
                             "x":29,
                             "y":99
                            }, 
                            {
                             "height":0,
                             "id":3,
                             "name":"",
                             "polygon":[
                                    {
                                     "x":0,
                                     "y":0
                                    }, 
                                    {
                                     "x":67,
                                     "y":4
                                    }, 
                                    {
                                     "x":73,
                                     "y":11
                                    }, 
                                    {
                                     "x":73,
                                     "y":17
                                    }, 
                                    {
                                     "x":68,
                                     "y":22
                                    }, 
                                    {
                                     "x":0,
                                     "y":28
                                    }],
                             "rotation":0,
                             "type":"",
                             "visible":true,
                             "width":0,
                             "x":115,
                             "y":87
                            }, 
                            {
                             "height":0,
                             "id":4,
                             "name":"",
                             "polygon":[
                                    {
                                     "x":0,
                                     "y":0
                                    }, 
                                    {
                                     "x":-17,
                                     "y":-22
                                    }, 
                                    {
                                     "x":-27,
                                     "y":-46
                                    }, 
                                    {
                                     "x":-18,
                                     "y":-46
                                    }, 
                                    {
                                     "x":39,
                                     "y":1
                                    }],
                             "rotation":0,
                             "type":"",
                             "visible":true,
                             "width":0,
                             "x":39,
                             "y":70
                            }, 
                            {
                             "height":0,
                             "id":5,
                             "name":"",
                             "polygon":[
                                    {
                                     "x":0,
                                     "y":0
                                    }, 
                                    {
                                     "x":-15,
                                     "y":23
                                    }, 
                                    {
                                     "x":-26,
                                     "y":46
                                    }, 
                                    {
                                     "x":-17,
                                     "y":47
                                    }, 
                                    {
                                     "x":40,
                                     "y":-1
                                    }],
                             "rotation":0,
                             "type":"",
                             "visible":true,
                             "width":0,
                             "x":37,
                             "y":130
                            }],
                     "opacity":1,
                     "type":"objectgroup",
                     "visible":true,
                     "x":0,
                     "y":0
                    }
                }],
         "tilewidth":200
        }, 
        {
         "columns":1,
         "firstgid":2,
         "image":"..\/..\/..\/Client\/Textures\/Effects\/Exhausts\/ExhaustYellowRectangular.png",
         "imageheight":224,
         "imagewidth":91,
         "margin":0,
         "name":"Exhausts",
         "spacing":0,
         "tilecount":8,
         "tileheight":28,
         "tiles":[
                {
                 "animation":[
                        {
                         "duration":40,
                         "tileid":0
                        }, 
                        {
                         "duration":40,
                         "tileid":1
                        }, 
                        {
                         "duration":40,
                         "tileid":2
                        }, 
                        {
                         "duration":40,
                         "tileid":3
                        }, 
                        {
                         "duration":40,
                         "tileid":4
                        }, 
                        {
                         "duration":40,
                         "tileid":5
                        }, 
                        {
                         "duration":40,
                         "tileid":6
                        }, 
                        {
                         "duration":100,
                         "tileid":7
                        }],
                 "id":7
                }],
         "tilewidth":91
        }],
 "tilewidth":200,
 "type":"map",
 "version":1.2,
 "width":1
}